ugoki/__init__.py
ugoki/cli.py
ugoki/config.py
ugoki/database.py
ugoki/main.py
ugoki/models.py
ugoki/schemas.py
ugoki-1.0.3.dist-info/entry_points.txt
ugoki-1.0.3.dist-info/LICENSE
ugoki-1.0.3.dist-info/WHEEL
ugoki-1.0.3.dist-info/METADATA
ugoki-1.0.3.dist-info/RECORD
