Metadata-Version: 2.1
Name: ugoki
Version: 1.0.3
Summary: API Server to serve random gifs with support for public suggestions
Home-page: https://gitlab.com/ceda_ei/ugoki.git
License: AGPL-3.0
Author: Ceda EI
Author-email: ceda_ei@webionite.com
Requires-Python: >=3.7,<4.0
Classifier: License :: OSI Approved :: GNU Affero General Public License v3
Classifier: Programming Language :: Python :: 3
Classifier: Programming Language :: Python :: 3.7
Classifier: Programming Language :: Python :: 3.8
Classifier: Programming Language :: Python :: 3.9
Requires-Dist: SQLAlchemy (>=1.4.25,<2.0.0)
Requires-Dist: aiofiles (>=0.7.0,<0.8.0)
Requires-Dist: fastapi (>=0.68.1,<0.69.0)
Requires-Dist: pydantic (>=1.8.2,<2.0.0)
Requires-Dist: python-multipart (>=0.0.5,<0.0.6)
Requires-Dist: uvicorn[standard] (>=0.15.0,<0.16.0)
Project-URL: Repository, https://gitlab.com/ceda_ei/ugoki.git
